LICENSE
MANIFEST.in
README.md
setup.py
hevea/Makefile
hevea/__init__.py
hevea/handler.py
hevea.egg-info/PKG-INFO
hevea.egg-info/SOURCES.txt
hevea.egg-info/dependency_links.txt
hevea.egg-info/not-zip-safe
hevea.egg-info/requires.txt
hevea.egg-info/top_level.txt
scripts/hevea