Metadata-Version: 1.1
Name: hevea
Version: 0.2
Summary: Monitor and compile LaTeX files
Home-page: https://github.com/yurimalheiros/hevea/
Author: Yuri Malheiros
Author-email: contato@yurimalheiros.com
License: Copyright © 2013 Yuri Malheiros
